common/__init__.py
common/admin.py
common/apps.py
common/celery.py
common/fields.py
common/forms.py
common/ftl-email.py
common/layout.py
common/logger.py
common/middleware.py
common/model_views.py
common/model_views_tree.py
common/models.py
common/reports.py
common/test_common.py
common/testcase.py
common/urls.py
common/utils.py
common/views.py
common/widgets.py
common/management/commands/export_users.py
common/migrations/0001_initial.py
common/migrations/0002_auto_20200412_1700.py
common/migrations/0003_auto_20200505_1607.py
common/migrations/0004_rota.py
common/migrations/0005_alter_configuracao_created_by_and_more.py
common/migrations/__init__.py
common/static/admin/css/autocomplete.css
common/static/admin/css/autocomplete.min.css
common/static/css/AdminLTE_custom.css
common/static/css/AdminLTE_custom.min.css
common/static/css/bootstrap-theme.css
common/static/css/bootstrap-theme.min.css
common/static/css/datatables.css
common/static/css/datatables.min.css
common/static/css/datepicker.css
common/static/css/fixedColumns.bootstrap.min.css
common/static/css/ftl.css
common/static/css/ftl.min.css
common/static/css/ionicons.css
common/static/css/ionicons.min.css
common/static/css/skin-blue.css
common/static/css/skin-blue.min.css
common/static/css/.sass-cache/c1e177425a75d7a50f165846228c0e3ba9ceed4a/xx.scssc
common/static/css/colors/blue.css
common/static/css/colors/brown.css
common/static/css/colors/brown2.css
common/static/css/colors/darkblue.css
common/static/css/colors/gold.css
common/static/css/colors/green.css
common/static/css/colors/green2.css
common/static/css/colors/lightblue.css
common/static/css/colors/purple.css
common/static/css/colors/salmon.css
common/static/css/colors/seagreen.css
common/static/css/colors/violetred.css
common/static/css/images/ui-bg_diagonals-thick_18_b81900_40x40.png
common/static/css/images/ui-bg_diagonals-thick_20_666666_40x40.png
common/static/css/images/ui-bg_flat_10_000000_40x100.png
ftlbase-1.17.dist-info/LICENSE
ftlbase-1.17.dist-info/METADATA
ftlbase-1.17.dist-info/WHEEL
ftlbase-1.17.dist-info/top_level.txt
ftlbase-1.17.dist-info/RECORD
