Metadata-Version: 2.1
Name: ftlbase
Version: 1.17
Summary: FTL Base Infrastructure
Home-page: https://github.com/waslucena/ftlbase
Author: Washington Lucena
Author-email: yourname@example.com
License: MIT
Keywords: django
Platform: UNKNOWN
Classifier: Environment :: Web Environment
Classifier: Framework :: Django
Classifier: Framework :: Django :: 4.2
Classifier: Intended Audience :: Developers
Classifier: License :: OSI Approved :: MIT License
Classifier: Operating System :: OS Independent
Classifier: Programming Language :: Python
Classifier: Programming Language :: Python :: 3.10
Classifier: Topic :: Internet :: WWW/HTTP :: Dynamic Content
License-File: LICENSE
